gbmarrsmodules/__init__.py
gbmarrsmodules/common.py
gbmarrsmodules/miriamRegex.py
gbmarrsmodules/namespaces.py
gbmarrsmodules/project_graph_modules.py
gbmarrsmodules/rdfWriterValidated.py
gbmarrsmodules/rdfstream.py
gbmarrsmodules/util.py
fastql_server-0.0.2.dist-info/LICENSE
fastql_server-0.0.2.dist-info/METADATA
fastql_server-0.0.2.dist-info/WHEEL
fastql_server-0.0.2.dist-info/top_level.txt
fastql_server-0.0.2.dist-info/RECORD
